hypothesis_mongoengine/__init__.py
hypothesis_mongoengine/geojson.py
hypothesis_mongoengine/helpers.py
hypothesis_mongoengine/strategies.py
hypothesis_mongoengine-2.0.0.dist-info/LICENSE.txt
hypothesis_mongoengine-2.0.0.dist-info/METADATA
hypothesis_mongoengine-2.0.0.dist-info/WHEEL
hypothesis_mongoengine-2.0.0.dist-info/top_level.txt
hypothesis_mongoengine-2.0.0.dist-info/RECORD
