Metadata-Version: 2.1
Name: hypothesis-mongoengine
Version: 2.0.0
Summary: Hypothesis strategy for MongoEngine models
Author-email: George Macon <george.macon@gmail.com>
Project-URL: Source, https://github.com/gmacon/hypothesis-mongoengine
Project-URL: Issues, https://github.com/gmacon/hypothesis-mongoengine/issues
Project-URL: Changelog, https://github.com/gmacon/hypothesis-mongoengine/blob/main/CHANGELOG.md
Classifier: Development Status :: 4 - Beta
Classifier: Intended Audience :: Developers
Classifier: License :: OSI Approved :: MIT License
Classifier: Programming Language :: Python :: 3
Classifier: Programming Language :: Python :: 3.9
Classifier: Programming Language :: Python :: 3.10
Classifier: Programming Language :: Python :: 3.11
Classifier: Programming Language :: Python :: 3.12
Classifier: Programming Language :: Python :: 3.13
Classifier: Topic :: Software Development :: Testing
Classifier: Framework :: Hypothesis
Requires-Python: >=3.9
License-File: LICENSE.txt
Requires-Dist: hypothesis
Requires-Dist: mongoengine
Provides-Extra: dev
Requires-Dist: ruff ; extra == 'dev'
Provides-Extra: tests
Requires-Dist: pytest ; extra == 'tests'
